tjson5parser.cp312-win_amd64.pyd
tjson5/__init__.py
tjson5-0.1.7.dist-info/LICENSE
tjson5-0.1.7.dist-info/METADATA
tjson5-0.1.7.dist-info/WHEEL
tjson5-0.1.7.dist-info/top_level.txt
tjson5-0.1.7.dist-info/RECORD
